gamedevtools/__init__.py
gamedevtools/helpers.py
gamedevtools/py.typed
gamedevtools/archives/rotate_archives.py
gamedevtools/archives/upload_archives.py
gamedevtools/s3/__init__.py
gamedevtools/s3/s3_client.py
gamedevtools-1.0.3.dist-info/METADATA
gamedevtools-1.0.3.dist-info/WHEEL
gamedevtools-1.0.3.dist-info/entry_points.txt
gamedevtools-1.0.3.dist-info/licenses/LICENSE
gamedevtools-1.0.3.dist-info/RECORD
