Metadata-Version: 2.4
Name: GameDevTools
Version: 1.0.3
Summary: Collection of Python tools to help with game development
Project-URL: Changelog, https://github.com/TheEmidee/PyGameDevTools/releases
Project-URL: Homepage, https://github.com/TheEmidee/PyGameDevTools
Project-URL: Source, https://github.com/TheEmidee/PyGameDevTools
Project-URL: Tracker, https://github.com/TheEmidee/PyGameDevTools/issues
Author-email: Michael Delva <michael@emidee.net>
Maintainer-email: Michael Delva <michael@emidee.net>
License: MIT License
License-File: LICENSE
Keywords: game development
Classifier: Development Status :: 5 - Production/Stable
Classifier: Intended Audience :: Developers
Classifier: Operating System :: Microsoft :: Windows
Classifier: Programming Language :: Python :: 3.11
Classifier: Topic :: Software Development :: Libraries
Classifier: Topic :: Utilities
Requires-Python: >=3.11
Requires-Dist: boto3
Requires-Dist: boto3-stubs[s3]
Requires-Dist: botocore
Requires-Dist: invoke
Requires-Dist: tqdm
Requires-Dist: types-invoke
Requires-Dist: types-tqdm
Provides-Extra: dev
Requires-Dist: build; extra == 'dev'
Requires-Dist: hatchling; extra == 'dev'
Requires-Dist: mypy; extra == 'dev'
Requires-Dist: ruff; extra == 'dev'
Requires-Dist: towncrier; extra == 'dev'
Requires-Dist: twine; extra == 'dev'
Requires-Dist: wheel; extra == 'dev'
Provides-Extra: dist
Requires-Dist: build; extra == 'dist'
Requires-Dist: hatchling; extra == 'dist'
Requires-Dist: towncrier; extra == 'dist'
Requires-Dist: twine; extra == 'dist'
Requires-Dist: wheel; extra == 'dist'
Provides-Extra: lint
Requires-Dist: mypy; extra == 'lint'
Requires-Dist: ruff; extra == 'lint'
